fga_demo/__init__.py
fga_demo/cli/__init__.py
fga_demo/cli/cli.py
fga_demo/cli/state_manager.py
fga_demo/cli/terraform_interface.py
fga_demo/cli/utils.py
fga_demo/cli/validation.py
fga_demo/terraform/.gitignore
fga_demo/terraform/README.md
fga_demo/terraform/main.tf
fga_demo-0.1.9.dist-info/METADATA
fga_demo-0.1.9.dist-info/WHEEL
fga_demo-0.1.9.dist-info/entry_points.txt
fga_demo-0.1.9.dist-info/RECORD
